click_anno/__init__.py
click_anno/core.py
click_anno/injectors.py
click_anno/snake_case.py
click_anno/types.py
click_anno/utils.py
click_anno-0.1.4.dist-info/LICENSE
click_anno-0.1.4.dist-info/METADATA
click_anno-0.1.4.dist-info/WHEEL
click_anno-0.1.4.dist-info/top_level.txt
click_anno-0.1.4.dist-info/RECORD
