Metadata-Version: 2.1
Name: click-anno
Version: 0.1.4
Summary: UNKNOWN
Home-page: https://github.com/Cologler/click-anno-python
Author: Cologler
Author-email: skyoflw@gmail.com
License: MIT License
Keywords: click
Platform: UNKNOWN
Requires-Dist: click
